kluster/__init__.py
kluster/api/schema.py
kluster/builders.py
kluster/contrib/__init__.py
kluster/contrib/arkitekt_repository.py
kluster/deployed.py
kluster/deployments/test/configs/gateway.yaml
kluster/deployments/test/configs/kluster.yaml
kluster/deployments/test/docker-compose.yml
kluster/deployments/test/public_key.pem
kluster/errrors.py
kluster/funcs.py
kluster/kluster.py
kluster/rath.py
kluster/repository.py
kluster/structures.py
kluster/traits.py
kluster-0.0.3.dist-info/LICENSE
kluster-0.0.3.dist-info/METADATA
kluster-0.0.3.dist-info/WHEEL
kluster-0.0.3.dist-info/RECORD
