Metadata-Version: 2.1
Name: kluster
Version: 0.0.3
Summary: omero images, but graphql
License: CC BY-NC 3.0
Author: jhnnsrs
Author-email: jhnnsrs@gmail.com
Requires-Python: >=3.9,<4.0
Classifier: License :: Other/Proprietary License
Classifier: Programming Language :: Python :: 3
Classifier: Programming Language :: Python :: 3.9
Classifier: Programming Language :: Python :: 3.10
Classifier: Programming Language :: Python :: 3.11
Provides-Extra: turms
Requires-Dist: dask-gateway (>=2023.9.0,<2024.0.0)
Requires-Dist: dokker (>=0.1.19)
Requires-Dist: rath (>=0.5.0)
